{"full_name": "Vidya Sudarshan", "designation": "Lecturer, School of Computer Science and Engineering", "email": "vidya.sudarshan@ntu.edu.sg", "image_path": "./profile_img/vidya_sudarshan.jpg", "biography": "Vidya Sudarshan is a Lecturer at School of Computer Science and Engineering (SCSE) in Nanyang Technological University (NTU). She received her PhD from Nanyang Technological University (NTU), Singapore and has more than 15+ years of research and teaching experience. Her main research expertise is in medical data mining, time series prediction, image and bio-signal processing, deep learning, Intelligent systems and AI applications. She has published more than 40 research papers in high impact factor journals.", "grants": "Assessing the effectiveness of interdisciplinary teams on learning and  assessment for STEM versus non-STEM students", "google_scholar": null, "orcid": null, "github": null, "scopus": null, "web_of_science": null, "dr_ntu": "https://dr.ntu.edu.sg/cris/rp/rp01361", "other_websites": [], "bachelor_degree": null, "masters": null, "phd": "Nanyang Technological University (NTU), Singapore"}