{"publications": [{"title_link": "https://scholar.google.com/citations?view_op=view_citation&hl=en&user=DhtAFkwAAAAJ&citation_for_view=DhtAFkwAAAAJ:ALROH1vI_8AC", "title": "Deep Residual Learning for Image Recognition", "published_by": "Computer Vision and Pattern Recognition (CVPR), 2016, 2016", "authors": ["K He", "X Zhang", "S Ren", "J Sun"], "cited_by_link": "https://scholar.google.com/scholar?oi=bibs&hl=en&cites=9281510746729853742,11322046990885118257,8079896737065463995,17634140231156417900,4525853235436727068,2525577079804777461,14586216232957520117,11959310692367127788,12028619717536592779,689112296523887923,16013406159877531928,7546803073980351828,17590291061863551079,15417811103964742246,3318125700009504314,7461781761399867363", "cited_by": 189972, "year": 2016}, {"title_link": "https://scholar.google.com/citations?view_op=view_citation&hl=en&user=DhtAFkwAAAAJ&citation_for_view=DhtAFkwAAAAJ:uDGL6kOW6j0C", "title": "Faster R-CNN: Towards Real-Time Object Detection with Region Proposal Networks", "published_by": "Neural Information Processing Systems (NIPS), 2015, 2015", "authors": ["S Ren", "K He", "R Girshick", "J Sun"], "cited_by_link": "https://scholar.google.com/scholar?oi=bibs&hl=en&cites=16436232259506318906,17860938601597205937,16974332364964810772,3633728273429114216", "cited_by": 66131, "year": 2015}, {"title_link": "https://scholar.google.com/citations?view_op=view_citation&hl=en&user=DhtAFkwAAAAJ&citation_for_view=DhtAFkwAAAAJ:jU7OWUQzBzMC", "title": "Mask R-CNN", "published_by": "International Conference on Computer Vision (ICCV), 2017, 2017", "authors": ["K He", "G Gkioxari", "P Doll\u00e1r", "R Girshick"], "cited_by_link": "https://scholar.google.com/scholar?oi=bibs&hl=en&cites=11459229647356475672,857777403106928327,15197155015620694395,4000254573761595905,16793008474347237102,9870998330890628693,3765419788986985300,8531310467268500856,2167755281724911886,12030520573284015181,8592274272403652632,1772532831502666757,806612534935273301,4157715937348738422,5401562535135710031,2111350715321307453,10723315583014316688,17781537337434386039", "cited_by": 31049, "year": 2017}, {"title_link": "https://scholar.google.com/citations?view_op=view_citation&hl=en&user=DhtAFkwAAAAJ&citation_for_view=DhtAFkwAAAAJ:3NQIlFlcGxIC", "title": "Focal Loss for Dense Object Detection", "published_by": "International Conference on Computer Vision (ICCV), 2017, 2017", "authors": ["TY Lin", "P Goyal", "R Girshick", "K He", "P Doll\u00e1r"], "cited_by_link": "https://scholar.google.com/scholar?oi=bibs&hl=en&cites=1010598353453664537,1273743886255047805,8492771696829395316,13411261072069911420,1864537485024430956,8165043485124878718", "cited_by": 25057, "year": 2017}, {"title_link": "https://scholar.google.com/citations?view_op=view_citation&hl=en&user=DhtAFkwAAAAJ&citation_for_view=DhtAFkwAAAAJ:CaZNVDsoPx4C", "title": "Delving Deep into Rectifiers: Surpassing Human-Level Performance on ImageNet Classification", "published_by": "International Conference on Computer Vision (ICCV), 2015, 2015", "authors": ["K He", "X Zhang", "S Ren", "J Sun"], "cited_by_link": "https://scholar.google.com/scholar?oi=bibs&hl=en&cites=6243061688889140249,13170054752862678792,13460341482797293737,1353440991044172895", "cited_by": 22341, "year": 2015}, {"title_link": "https://scholar.google.com/citations?view_op=view_citation&hl=en&user=DhtAFkwAAAAJ&citation_for_view=DhtAFkwAAAAJ:WHdLCjDvYFkC", "title": "Feature Pyramid Networks for Object Detection", "published_by": "Computer Vision and Pattern Recognition (CVPR), 2017, 2017", "authors": ["TY Lin", "P Doll\u00e1r", "R Girshick", "K He", "B Hariharan", "S Belongie"], "cited_by_link": "https://scholar.google.com/scholar?oi=bibs&hl=en&cites=13353537855176955572,3805748966480583316,5523349418399288959", "cited_by": 22112, "year": 2017}, {"title_link": "https://scholar.google.com/citations?view_op=view_citation&hl=en&user=DhtAFkwAAAAJ&citation_for_view=DhtAFkwAAAAJ:u-coK7KVo8oC", "title": "Spatial Pyramid Pooling in Deep Convolutional Networks for Visual Recognition", "published_by": "European Conference on Computer Vision (ECCV), 2014, 2014", "authors": ["K He", "X Zhang", "S Ren", "J Sun"], "cited_by_link": "https://scholar.google.com/scholar?oi=bibs&hl=en&cites=15950430662967917123", "cited_by": 13655, "year": 2014}, {"title_link": "https://scholar.google.com/citations?view_op=view_citation&hl=en&user=DhtAFkwAAAAJ&citation_for_view=DhtAFkwAAAAJ:PaBasH6fAo0C", "title": "Learning a Deep Convolutional Network for Image Super-Resolution", "published_by": "European Conference on Computer Vision (ECCV), 2014, 2014", "authors": ["C Dong", "CC Loy", "K He", "X Tang"], "cited_by_link": "https://scholar.google.com/scholar?oi=bibs&hl=en&cites=13705212607084119344,12401256383167717427", "cited_by": 12731, "year": 2014}, {"title_link": "https://scholar.google.com/citations?view_op=view_citation&hl=en&user=DhtAFkwAAAAJ&citation_for_view=DhtAFkwAAAAJ:ubry08Y2EpUC", "title": "Identity Mappings in Deep Residual Networks", "published_by": "European Conference on Computer Vision (ECCV), 2016, 2016", "authors": ["K He", "X Zhang", "S Ren", "J Sun"], "cited_by_link": "https://scholar.google.com/scholar?oi=bibs&hl=en&cites=14035416619237709781,12506622340387284078,17156217292086540643,1777334842773378135", "cited_by": 10861, "year": 2016}, {"title_link": "https://scholar.google.com/citations?view_op=view_citation&hl=en&user=DhtAFkwAAAAJ&citation_for_view=DhtAFkwAAAAJ:MpfHP-DdYjUC", "title": "Aggregated Residual Transformations for Deep Neural Networks", "published_by": "Computer Vision and Pattern Recognition (CVPR), 2017, 2017", "authors": ["S Xie", "R Girshick", "P Doll\u00e1r", "Z Tu", "K He"], "cited_by_link": "https://scholar.google.com/scholar?oi=bibs&hl=en&cites=11890020786646058356,10727059203928927892", "cited_by": 10824, "year": 2017}, {"title_link": "https://scholar.google.com/citations?view_op=view_citation&hl=en&user=DhtAFkwAAAAJ&citation_for_view=DhtAFkwAAAAJ:DBa1UEJaJKAC", "title": "Non-local Neural Networks", "published_by": "Computer Vision and Pattern Recognition (CVPR), 2018, 2018", "authors": ["X Wang", "R Girshick", "A Gupta", "K He"], "cited_by_link": "https://scholar.google.com/scholar?oi=bibs&hl=en&cites=10047890866676489078", "cited_by": 9240, "year": 2018}, {"title_link": "https://scholar.google.com/citations?view_op=view_citation&hl=en&user=DhtAFkwAAAAJ&citation_for_view=DhtAFkwAAAAJ:3bvyWxjaHKcC", "title": "Momentum Contrast for Unsupervised Visual Representation Learning", "published_by": "Computer Vision and Pattern Recognition (CVPR), 2020, 2020", "authors": ["K He", "H Fan", "Y Wu", "S Xie", "R Girshick"], "cited_by_link": "https://scholar.google.com/scholar?oi=bibs&hl=en&cites=14818266289376344383,9483061155297685449", "cited_by": 8984, "year": 2020}, {"title_link": "https://scholar.google.com/citations?view_op=view_citation&hl=en&user=DhtAFkwAAAAJ&citation_for_view=DhtAFkwAAAAJ:3fE2CSJIrl8C", "title": "Single Image Haze Removal using Dark Channel Prior", "published_by": "Computer Vision and Pattern Recognition (CVPR), 2009, 2009", "authors": ["K He", "J Sun", "X Tang"], "cited_by_link": "https://scholar.google.com/scholar?oi=bibs&hl=en&cites=11452018541640230539,12881729615275247156", "cited_by": 8205, "year": 2009}, {"title_link": "https://scholar.google.com/citations?view_op=view_citation&hl=en&user=DhtAFkwAAAAJ&citation_for_view=DhtAFkwAAAAJ:buQ7SEKw-1sC", "title": "Guided Image Filtering", "published_by": "European Conference on Computer Vision (ECCV), 2010, 2010", "authors": ["K He", "J Sun", "X Tang"], "cited_by_link": "https://scholar.google.com/scholar?oi=bibs&hl=en&cites=11575470123647071266", "cited_by": 7695, "year": 2010}, {"title_link": "https://scholar.google.com/citations?view_op=view_citation&hl=en&user=DhtAFkwAAAAJ&citation_for_view=DhtAFkwAAAAJ:BzfGm06jWhQC", "title": "R-FCN: Object Detection via Region-based Fully Convolutional Networks", "published_by": "Neural Information Processing Systems (NIPS), 2016, 2016", "authors": ["J Dai", "Y Li", "K He", "J Sun"], "cited_by_link": "https://scholar.google.com/scholar?oi=bibs&hl=en&cites=14880935744314366653,18293380539366842091", "cited_by": 6903, "year": 2016}, {"title_link": "https://scholar.google.com/citations?view_op=view_citation&hl=en&user=DhtAFkwAAAAJ&citation_for_view=DhtAFkwAAAAJ:XUvXOeBm_78C", "title": "Accurate, Large Minibatch SGD: Training ImageNet in 1 Hour", "published_by": "arXiv preprint arXiv:1706.02677, 2017", "authors": ["P Goyal", "P Doll\u00e1r", "R Girshick", "P Noordhuis", "L Wesolowski", "A Kyrola", "..."], "cited_by_link": "https://scholar.google.com/scholar?oi=bibs&hl=en&cites=9378071906526689990,4989201439731525312,12842227061084420467", "cited_by": 3521, "year": 2017}, {"title_link": "https://scholar.google.com/citations?view_op=view_citation&hl=en&user=DhtAFkwAAAAJ&citation_for_view=DhtAFkwAAAAJ:1Ye0OR6EYb4C", "title": "Group Normalization", "published_by": "European Conference on Computer Vision (ECCV), 2018, 2018", "authors": ["Y Wu", "K He"], "cited_by_link": "https://scholar.google.com/scholar?oi=bibs&hl=en&cites=14814179610283147593", "cited_by": 3370, "year": 2018}, {"title_link": "https://scholar.google.com/citations?view_op=view_citation&hl=en&user=DhtAFkwAAAAJ&citation_for_view=DhtAFkwAAAAJ:Xz60mAmATU4C", "title": "Masked Autoencoders Are Scalable Vision Learners", "published_by": "Computer Vision and Pattern Recognition (CVPR), 2022, 2022", "authors": ["K He", "X Chen", "S Xie", "Y Li", "P Doll\u00e1r", "R Girshick"], "cited_by_link": "https://scholar.google.com/scholar?oi=bibs&hl=en&cites=16837829726140559426", "cited_by": 3257, "year": 2022}, {"title_link": "https://scholar.google.com/citations?view_op=view_citation&hl=en&user=DhtAFkwAAAAJ&citation_for_view=DhtAFkwAAAAJ:BJbdYPG6LGMC", "title": "Convolutional Neural Networks at Constrained Time Cost", "published_by": "Computer Vision and Pattern Recognition (CVPR), 2015, 2015", "authors": ["K He", "J Sun"], "cited_by_link": "https://scholar.google.com/scholar?oi=bibs&hl=en&cites=8825404952865269038", "cited_by": 2872, "year": 2015}, {"title_link": "https://scholar.google.com/citations?view_op=view_citation&hl=en&user=DhtAFkwAAAAJ&citation_for_view=DhtAFkwAAAAJ:SnGPuo6Feq8C", "title": "Exploring Simple Siamese Representation Learning", "published_by": "Computer Vision and Pattern Recognition (CVPR), 2021, 2021", "authors": ["X Chen", "K He"], "cited_by_link": "https://scholar.google.com/scholar?oi=bibs&hl=en&cites=14102911635221168501", "cited_by": 2815, "year": 2021}, {"title_link": "https://scholar.google.com/citations?view_op=view_citation&hl=en&user=DhtAFkwAAAAJ&cstart=20&pagesize=80&citation_for_view=DhtAFkwAAAAJ:kWvqk_afx_IC", "title": "SlowFast Networks for Video Recognition", "published_by": "International Conference on Computer Vision (ICCV), 2019, 2019", "authors": ["C Feichtenhofer", "H Fan", "J Malik", "K He"], "cited_by_link": "https://scholar.google.com/scholar?oi=bibs&hl=en&cites=1892562522989461632,2906097696904585718", "cited_by": 2688, "year": 2019}, {"title_link": "https://scholar.google.com/citations?view_op=view_citation&hl=en&user=DhtAFkwAAAAJ&cstart=20&pagesize=80&citation_for_view=DhtAFkwAAAAJ:SGW5VrABaM0C", "title": "Improved Baselines with Momentum Contrastive Learning", "published_by": "arXiv preprint arXiv:2003.04297, 2020", "authors": ["X Chen", "H Fan", "R Girshick", "K He"], "cited_by_link": "https://scholar.google.com/scholar?oi=bibs&hl=en&cites=16650257291573763482,3275169092043997840", "cited_by": 2598, "year": 2020}, {"title_link": "https://scholar.google.com/citations?view_op=view_citation&hl=en&user=DhtAFkwAAAAJ&cstart=20&pagesize=80&citation_for_view=DhtAFkwAAAAJ:65Yg0jNCQDAC", "title": "An Empirical Study of Training Self-Supervised Vision Transformers", "published_by": "International Conference on Computer Vision (ICCV), 2021, 2021", "authors": ["X Chen", "S Xie", "K He"], "cited_by_link": "https://scholar.google.com/scholar?oi=bibs&hl=en&cites=7329647594369932315", "cited_by": 1733, "year": 2021}, {"title_link": "https://scholar.google.com/citations?view_op=view_citation&hl=en&user=DhtAFkwAAAAJ&cstart=20&pagesize=80&citation_for_view=DhtAFkwAAAAJ:jL-93Qbq4QoC", "title": "Instance-aware Semantic Segmentation via Multi-task Network Cascades", "published_by": "Computer Vision and Pattern Recognition (CVPR), 2016, 2016", "authors": ["J Dai", "K He", "J Sun"], "cited_by_link": "https://scholar.google.com/scholar?oi=bibs&hl=en&cites=7342374495730352680", "cited_by": 1569, "year": 2016}, {"title_link": "https://scholar.google.com/citations?view_op=view_citation&hl=en&user=DhtAFkwAAAAJ&cstart=20&pagesize=80&citation_for_view=DhtAFkwAAAAJ:-7ulzOJl1JYC", "title": "Exploring the Limits of Weakly Supervised Pretraining", "published_by": "European Conference on Computer Vision (ECCV), 2018, 2018", "authors": ["D Mahajan", "R Girshick", "V Ramanathan", "K He", "M Paluri", "Y Li", "A Bharambe", "..."], "cited_by_link": "https://scholar.google.com/scholar?oi=bibs&hl=en&cites=8358288919170046195", "cited_by": 1358, "year": 2018}, {"title_link": "https://scholar.google.com/citations?view_op=view_citation&hl=en&user=DhtAFkwAAAAJ&cstart=20&pagesize=80&citation_for_view=DhtAFkwAAAAJ:eO3_k5sD8BwC", "title": "Designing Network Design Spaces", "published_by": "Computer Vision and Pattern Recognition (CVPR), 2020, 2020", "authors": ["I Radosavovic", "RP Kosaraju", "R Girshick", "K He", "P Doll\u00e1r"], "cited_by_link": "https://scholar.google.com/scholar?oi=bibs&hl=en&cites=1436458088266741112,5875729847852467130", "cited_by": 1305, "year": 2020}, {"title_link": "https://scholar.google.com/citations?view_op=view_citation&hl=en&user=DhtAFkwAAAAJ&cstart=20&pagesize=80&citation_for_view=DhtAFkwAAAAJ:jFemdcug13IC", "title": "Panoptic Segmentation", "published_by": "Computer Vision and Pattern Recognition (CVPR), 2019, 2019", "authors": ["A Kirillov", "K He", "R Girshick", "C Rother", "P Doll\u00e1r"], "cited_by_link": "https://scholar.google.com/scholar?oi=bibs&hl=en&cites=5074178277454044798,16387520994368714372", "cited_by": 1272, "year": 2019}, {"title_link": "https://scholar.google.com/citations?view_op=view_citation&hl=en&user=DhtAFkwAAAAJ&cstart=20&pagesize=80&citation_for_view=DhtAFkwAAAAJ:AHdEip9mkN0C", "title": "BoxSup: Exploiting Bounding Boxes to Supervise Convolutional Networks for Semantic Segmentation", "published_by": "International Conference on Computer Vision (ICCV), 2015, 2015", "authors": ["J Dai", "K He", "J Sun"], "cited_by_link": "https://scholar.google.com/scholar?oi=bibs&hl=en&cites=10583411756105923851", "cited_by": 1144, "year": 2015}, {"title_link": "https://scholar.google.com/citations?view_op=view_citation&hl=en&user=DhtAFkwAAAAJ&cstart=20&pagesize=80&citation_for_view=DhtAFkwAAAAJ:U_HPUtbDl20C", "title": "Rethinking ImageNet Pre-training", "published_by": "International Conference on Computer Vision (ICCV), 2019, 2019", "authors": ["K He", "R Girshick", "P Doll\u00e1r"], "cited_by_link": "https://scholar.google.com/scholar?oi=bibs&hl=en&cites=8945175718646989267", "cited_by": 1136, "year": 2019}, {"title_link": "https://scholar.google.com/citations?view_op=view_citation&hl=en&user=DhtAFkwAAAAJ&cstart=20&pagesize=80&citation_for_view=DhtAFkwAAAAJ:-95Q15plzcUC", "title": "Panoptic Feature Pyramid Networks", "published_by": "Computer Vision and Pattern Recognition (CVPR), 2019, 2019", "authors": ["A Kirillov", "R Girshick", "K He", "P Doll\u00e1r"], "cited_by_link": "https://scholar.google.com/scholar?oi=bibs&hl=en&cites=4764353839421452842", "cited_by": 1095, "year": 2019}, {"title_link": "https://scholar.google.com/citations?view_op=view_citation&hl=en&user=DhtAFkwAAAAJ&cstart=20&pagesize=80&citation_for_view=DhtAFkwAAAAJ:zCSUwVk65WsC", "title": "ScribbleSup: Scribble-Supervised Convolutional Networks for Semantic Segmentation", "published_by": "Computer Vision and Pattern Recognition (CVPR), 2016, 2016", "authors": ["D Lin", "J Dai", "J Jia", "K He", "J Sun"], "cited_by_link": "https://scholar.google.com/scholar?oi=bibs&hl=en&cites=1344368443978557455", "cited_by": 1023, "year": 2016}, {"title_link": "https://scholar.google.com/citations?view_op=view_citation&hl=en&user=DhtAFkwAAAAJ&cstart=20&pagesize=80&citation_for_view=DhtAFkwAAAAJ:HhcuHIWmDEUC", "title": "Deep Hough Voting for 3D Object Detection in Point Clouds", "published_by": "International Conference on Computer Vision (ICCV), 2019, 2019", "authors": ["CR Qi", "O Litany", "K He", "LJ Guibas"], "cited_by_link": "https://scholar.google.com/scholar?oi=bibs&hl=en&cites=13828261800244123309", "cited_by": 1015, "year": 2019}, {"title_link": "https://scholar.google.com/citations?view_op=view_citation&hl=en&user=DhtAFkwAAAAJ&cstart=20&pagesize=80&citation_for_view=DhtAFkwAAAAJ:U4n9YNQMCAIC", "title": "Is Faster R-CNN Doing Well for Pedestrian Detection?", "published_by": "European Conference on Computer Vision (ECCV), 2016, 2016", "authors": ["L Zhang", "L Lin", "X Liang", "K He"], "cited_by_link": "https://scholar.google.com/scholar?oi=bibs&hl=en&cites=12199992810190996739", "cited_by": 994, "year": 2016}, {"title_link": "https://scholar.google.com/citations?view_op=view_citation&hl=en&user=DhtAFkwAAAAJ&cstart=20&pagesize=80&citation_for_view=DhtAFkwAAAAJ:NyGDZy8z5eUC", "title": "Accelerating Very Deep Convolutional Networks for Classification and Detection", "published_by": "IEEE Transactions on Pattern Analysis and Machine Intelligence (TPAMI), 2015", "authors": ["X Zhang", "J Zou", "K He", "J Sun"], "cited_by_link": "https://scholar.google.com/scholar?oi=bibs&hl=en&cites=11183077033015235296", "cited_by": 937, "year": 2015}, {"title_link": "https://scholar.google.com/citations?view_op=view_citation&hl=en&user=DhtAFkwAAAAJ&cstart=20&pagesize=80&citation_for_view=DhtAFkwAAAAJ:ce2CqMG-AY4C", "title": "Feature Denoising for Improving Adversarial Robustness", "published_by": "Computer Vision and Pattern Recognition (CVPR), 2019, 2019", "authors": ["C Xie", "Y Wu", "L van der Maaten", "A Yuille", "K He"], "cited_by_link": "https://scholar.google.com/scholar?oi=bibs&hl=en&cites=961363392550158116", "cited_by": 861, "year": 2019}, {"title_link": "https://scholar.google.com/citations?view_op=view_citation&hl=en&user=DhtAFkwAAAAJ&cstart=20&pagesize=80&citation_for_view=DhtAFkwAAAAJ:IaI1MmNe2tcC", "title": "Optimized Product Quantization for Approximate Nearest Neighbor Search", "published_by": "Computer Vision and Pattern Recognition (CVPR), 2013, 2013", "authors": ["T Ge", "K He", "Q Ke", "J Sun"], "cited_by_link": "https://scholar.google.com/scholar?oi=bibs&hl=en&cites=8916499381004060329,16986026928292175000", "cited_by": 741, "year": 2013}, {"title_link": "https://scholar.google.com/citations?view_op=view_citation&hl=en&user=DhtAFkwAAAAJ&cstart=20&pagesize=80&citation_for_view=DhtAFkwAAAAJ:w1MjKQ0l0TYC", "title": "PointRend: Image Segmentation as Rendering", "published_by": "Computer Vision and Pattern Recognition (CVPR), 2020, 2020", "authors": ["A Kirillov", "Y Wu", "K He", "R Girshick"], "cited_by_link": "https://scholar.google.com/scholar?oi=bibs&hl=en&cites=3835458723700933772", "cited_by": 739, "year": 2020}, {"title_link": "https://scholar.google.com/citations?view_op=view_citation&hl=en&user=DhtAFkwAAAAJ&cstart=20&pagesize=80&citation_for_view=DhtAFkwAAAAJ:L1USKYWJimsC", "title": "Detecting and Recognizing Human-Object Interactions", "published_by": "Computer Vision and Pattern Recognition (CVPR), 2018, 2018", "authors": ["G Gkioxari", "R Girshick", "P Doll\u00e1r", "K He"], "cited_by_link": "https://scholar.google.com/scholar?oi=bibs&hl=en&cites=3296937519903423167,1188752748932974452", "cited_by": 596, "year": 2018}, {"title_link": "https://scholar.google.com/citations?view_op=view_citation&hl=en&user=DhtAFkwAAAAJ&cstart=20&pagesize=80&citation_for_view=DhtAFkwAAAAJ:vDZJ-YLwNdEC", "title": "Convolutional Feature Masking for Joint Object and Stuff Segmentation", "published_by": "Computer Vision and Pattern Recognition (CVPR), 2015, 2015", "authors": ["J Dai", "K He", "J Sun"], "cited_by_link": "https://scholar.google.com/scholar?oi=bibs&hl=en&cites=16351799615487824726", "cited_by": 519, "year": 2015}, {"title_link": "https://scholar.google.com/citations?view_op=view_citation&hl=en&user=DhtAFkwAAAAJ&cstart=20&pagesize=80&citation_for_view=DhtAFkwAAAAJ:KaMxkj08jr0C", "title": "Detectron", "published_by": "https://github.com/facebookresearch/Detectron, 2018", "authors": ["R Girshick", "I Radosavovic", "G Gkioxari", "P Doll\u00e1r", "K He"], "cited_by_link": "https://scholar.google.com/scholar?oi=bibs&hl=en&cites=2722589238536914956,10008799752430860152", "cited_by": 516, "year": 2018}, {"title_link": "https://scholar.google.com/citations?view_op=view_citation&hl=en&user=DhtAFkwAAAAJ&cstart=20&pagesize=80&citation_for_view=DhtAFkwAAAAJ:jgBuDB5drN8C", "title": "Instance-sensitive Fully Convolutional Networks", "published_by": "European Conference on Computer Vision (ECCV), 2016, 2016", "authors": ["J Dai", "K He", "Y Li", "S Ren", "J Sun"], "cited_by_link": "https://scholar.google.com/scholar?oi=bibs&hl=en&cites=15993495353255568373", "cited_by": 494, "year": 2016}, {"title_link": "https://scholar.google.com/citations?view_op=view_citation&hl=en&user=DhtAFkwAAAAJ&cstart=20&pagesize=80&citation_for_view=DhtAFkwAAAAJ:sJsF-0ZLhtgC", "title": "Object Detection Networks on Convolutional Feature Maps", "published_by": "IEEE Transactions on Pattern Analysis and Machine Intelligence (TPAMI), 2016", "authors": ["S Ren", "K He", "R Girshick", "X Zhang", "J Sun"], "cited_by_link": "https://scholar.google.com/scholar?oi=bibs&hl=en&cites=6385320480924360974", "cited_by": 484, "year": 2016}, {"title_link": "https://scholar.google.com/citations?view_op=view_citation&hl=en&user=DhtAFkwAAAAJ&cstart=20&pagesize=80&citation_for_view=DhtAFkwAAAAJ:1DsIQWDZLl8C", "title": "Long-Term Feature Banks for Detailed Video Understanding", "published_by": "Computer Vision and Pattern Recognition (CVPR), 2019, 2019", "authors": ["CY Wu", "C Feichtenhofer", "H Fan", "K He", "P Kr\u00e4henb\u00fchl", "R Girshick"], "cited_by_link": "https://scholar.google.com/scholar?oi=bibs&hl=en&cites=12076206268409002970", "cited_by": 481, "year": 2019}, {"title_link": "https://scholar.google.com/citations?view_op=view_citation&hl=en&user=DhtAFkwAAAAJ&cstart=20&pagesize=80&citation_for_view=DhtAFkwAAAAJ:ufrVoPGSRksC", "title": "K-means hashing: An affinity-preserving quantization method for learning binary compact codes", "published_by": "Computer Vision and Pattern Recognition (CVPR), 2013, 2013", "authors": ["K He", "F Wen", "J Sun"], "cited_by_link": "https://scholar.google.com/scholar?oi=bibs&hl=en&cites=9783752059076362243", "cited_by": 469, "year": 2013}, {"title_link": "https://scholar.google.com/citations?view_op=view_citation&hl=en&user=DhtAFkwAAAAJ&cstart=20&pagesize=80&citation_for_view=DhtAFkwAAAAJ:6_hjMsCP8ZoC", "title": "Data Distillation: Towards Omni-Supervised Learning", "published_by": "Computer Vision and Pattern Recognition (CVPR), 2018, 2018", "authors": ["I Radosavovic", "P Doll\u00e1r", "R Girshick", "G Gkioxari", "K He"], "cited_by_link": "https://scholar.google.com/scholar?oi=bibs&hl=en&cites=10322455634321211671", "cited_by": 435, "year": 2018}, {"title_link": "https://scholar.google.com/citations?view_op=view_citation&hl=en&user=DhtAFkwAAAAJ&cstart=20&pagesize=80&citation_for_view=DhtAFkwAAAAJ:Y0pCki6q_DkC", "title": "Statistics of Patch Offsets for Image Completion", "published_by": "European Conference on Computer Vision (ECCV), 2012, 2012", "authors": ["K He", "J Sun"], "cited_by_link": "https://scholar.google.com/scholar?oi=bibs&hl=en&cites=7932532670050182242,13439706714561828674,3615136994266582926", "cited_by": 423, "year": 2012}, {"title_link": "https://scholar.google.com/citations?view_op=view_citation&hl=en&user=DhtAFkwAAAAJ&cstart=20&pagesize=80&citation_for_view=DhtAFkwAAAAJ:pAkWuXOU-OoC", "title": "Exploring Randomly Wired Neural Networks for Image Recognition", "published_by": "International Conference on Computer Vision (ICCV), 2019, 2019", "authors": ["S Xie", "A Kirillov", "R Girshick", "K He"], "cited_by_link": "https://scholar.google.com/scholar?oi=bibs&hl=en&cites=15284102476154990419", "cited_by": 391, "year": 2019}, {"title_link": "https://scholar.google.com/citations?view_op=view_citation&hl=en&user=DhtAFkwAAAAJ&cstart=20&pagesize=80&citation_for_view=DhtAFkwAAAAJ:2osOgNQ5qMEC", "title": "A Global Sampling Method for Alpha Matting", "published_by": "Computer Vision and Pattern Recognition (CVPR), 2011, 2011", "authors": ["K He", "C Rhemann", "C Rother", "X Tang", "J Sun"], "cited_by_link": "https://scholar.google.com/scholar?oi=bibs&hl=en&cites=18311212590806817515,611431405697702756,8105772327483535261", "cited_by": 383, "year": 2011}, {"title_link": "https://scholar.google.com/citations?view_op=view_citation&hl=en&user=DhtAFkwAAAAJ&cstart=20&pagesize=80&citation_for_view=DhtAFkwAAAAJ:uVUOdF_882EC", "title": "TensorMask: A Foundation for Dense Object Segmentation", "published_by": "International Conference on Computer Vision (ICCV), 2019, 2019", "authors": ["X Chen", "R Girshick", "K He", "P Doll\u00e1r"], "cited_by_link": "https://scholar.google.com/scholar?oi=bibs&hl=en&cites=9523141505186469043", "cited_by": 355, "year": 2019}, {"title_link": "https://scholar.google.com/citations?view_op=view_citation&hl=en&user=DhtAFkwAAAAJ&cstart=20&pagesize=80&citation_for_view=DhtAFkwAAAAJ:ULOm3_A8WrAC", "title": "Constant Time Weighted Median Filtering for Stereo Matching and Beyond", "published_by": "International Conference on Computer Vision (ICCV), 2013, 2013", "authors": ["Z Ma", "K He", "Y Wei", "J Sun", "E Wu"], "cited_by_link": "https://scholar.google.com/scholar?oi=bibs&hl=en&cites=10749781702433795385", "cited_by": 349, "year": 2013}, {"title_link": "https://scholar.google.com/citations?view_op=view_citation&hl=en&user=DhtAFkwAAAAJ&cstart=20&pagesize=80&citation_for_view=DhtAFkwAAAAJ:q-HalDI95KYC", "title": "Learning to Segment Every Thing", "published_by": "Computer Vision and Pattern Recognition (CVPR), 2018, 2018", "authors": ["R Hu", "P Doll\u00e1r", "K He", "T Darrell", "R Girshick"], "cited_by_link": "https://scholar.google.com/scholar?oi=bibs&hl=en&cites=12649479254092732461", "cited_by": 323, "year": 2018}, {"title_link": "https://scholar.google.com/citations?view_op=view_citation&hl=en&user=DhtAFkwAAAAJ&cstart=20&pagesize=80&citation_for_view=DhtAFkwAAAAJ:YlPif8NxrbYC", "title": "Exploring Plain Vision Transformer Backbones for Object Detection", "published_by": "European Conference on Computer Vision (ECCV), 2022, 2022", "authors": ["Y Li", "H Mao", "R Girshick", "K He"], "cited_by_link": "https://scholar.google.com/scholar?oi=bibs&hl=en&cites=4490918786976048296", "cited_by": 320, "year": 2022}, {"title_link": "https://scholar.google.com/citations?view_op=view_citation&hl=en&user=DhtAFkwAAAAJ&cstart=20&pagesize=80&citation_for_view=DhtAFkwAAAAJ:artPoR2Yc-kC", "title": "Efficient and Accurate Approximations of Nonlinear Convolutional Networks", "published_by": "Computer Vision and Pattern Recognition (CVPR), 2015, 2015", "authors": ["X Zhang", "J Zou", "X Ming", "K He", "J Sun"], "cited_by_link": "https://scholar.google.com/scholar?oi=bibs&hl=en&cites=4906398807705843424", "cited_by": 312, "year": 2015}, {"title_link": "https://scholar.google.com/citations?view_op=view_citation&hl=en&user=DhtAFkwAAAAJ&cstart=20&pagesize=80&citation_for_view=DhtAFkwAAAAJ:6yz0xqPARnAC", "title": "Fast Guided Filter", "published_by": "arXiv preprint arXiv:1505.00996, 2015", "authors": ["K He", "J Sun"], "cited_by_link": "https://scholar.google.com/scholar?oi=bibs&hl=en&cites=13767952820030426664", "cited_by": 258, "year": 2015}, {"title_link": "https://scholar.google.com/citations?view_op=view_citation&hl=en&user=DhtAFkwAAAAJ&cstart=20&pagesize=80&citation_for_view=DhtAFkwAAAAJ:d1gkVwhDpl0C", "title": "Fast Matting using Large Kernel Matting Laplacian Matrices", "published_by": "Computer Vision and Pattern Recognition (CVPR), 2010, 2010", "authors": ["K He", "J Sun", "X Tang"], "cited_by_link": "https://scholar.google.com/scholar?oi=bibs&hl=en&cites=16926294974549070594,1230723370230194774", "cited_by": 217, "year": 2010}, {"title_link": "https://scholar.google.com/citations?view_op=view_citation&hl=en&user=DhtAFkwAAAAJ&cstart=20&pagesize=80&citation_for_view=DhtAFkwAAAAJ:eGYfIraVYiQC", "title": "Masked Autoencoders As Spatiotemporal Learners", "published_by": "Neural Information Processing Systems (NeurIPS), 2022, 2022", "authors": ["C Feichtenhofer", "H Fan", "Y Li", "K He"], "cited_by_link": "https://scholar.google.com/scholar?oi=bibs&hl=en&cites=5215096183189163093", "cited_by": 203, "year": 2022}, {"title_link": "https://scholar.google.com/citations?view_op=view_citation&hl=en&user=DhtAFkwAAAAJ&cstart=20&pagesize=80&citation_for_view=DhtAFkwAAAAJ:LPtt_HFRSbwC", "title": "Transitive Invariance for Self-supervised Visual Representation Learning", "published_by": "International Conference on Computer Vision (ICCV), 2017, 2017", "authors": ["X Wang", "K He", "A Gupta"], "cited_by_link": "https://scholar.google.com/scholar?oi=bibs&hl=en&cites=3757966986019272862", "cited_by": 193, "year": 2017}, {"title_link": "https://scholar.google.com/citations?view_op=view_citation&hl=en&user=DhtAFkwAAAAJ&cstart=20&pagesize=80&citation_for_view=DhtAFkwAAAAJ:UuEBAcK4md4C", "title": "A Large-Scale Study on Unsupervised Spatiotemporal Representation Learning", "published_by": "Computer Vision and Pattern Recognition (CVPR), 2021, 2021", "authors": ["C Feichtenhofer", "H Fan", "B Xiong", "R Girshick", "K He"], "cited_by_link": "https://scholar.google.com/scholar?oi=bibs&hl=en&cites=13005810490237461760", "cited_by": 188, "year": 2021}, {"title_link": "https://scholar.google.com/citations?view_op=view_citation&hl=en&user=DhtAFkwAAAAJ&cstart=20&pagesize=80&citation_for_view=DhtAFkwAAAAJ:Tyk-4Ss8FVUC", "title": "Computing Nearest-Neighbor Fields via Propagation-Assisted KD-Trees", "published_by": "Computer Vision and Pattern Recognition (CVPR), 2012, 2012", "authors": ["K He", "J Sun"], "cited_by_link": "https://scholar.google.com/scholar?oi=bibs&hl=en&cites=4751463594752218238", "cited_by": 175, "year": 2012}, {"title_link": "https://scholar.google.com/citations?view_op=view_citation&hl=en&user=DhtAFkwAAAAJ&cstart=20&pagesize=80&citation_for_view=DhtAFkwAAAAJ:_FxGoFyzp5QC", "title": "Rectangling Panoramic Images via Warping", "published_by": "ACM Transactions on Graphics (TOG) 32 (4), 79, 2013", "authors": ["K He", "H Chang", "J Sun"], "cited_by_link": "https://scholar.google.com/scholar?oi=bibs&hl=en&cites=18395074905223204497,4557402708878452921", "cited_by": 132, "year": 2013}, {"title_link": "https://scholar.google.com/citations?view_op=view_citation&hl=en&user=DhtAFkwAAAAJ&cstart=20&pagesize=80&citation_for_view=DhtAFkwAAAAJ:pS0ncopqnHgC", "title": "Graph Structure of Neural Networks", "published_by": "International Conference on Machine Learning (ICML), 2020, 2020", "authors": ["J You", "J Leskovec", "K He", "S Xie"], "cited_by_link": "https://scholar.google.com/scholar?oi=bibs&hl=en&cites=4649234253279793186", "cited_by": 128, "year": 2020}, {"title_link": "https://scholar.google.com/citations?view_op=view_citation&hl=en&user=DhtAFkwAAAAJ&cstart=20&pagesize=80&citation_for_view=DhtAFkwAAAAJ:-nhnvRiOwuoC", "title": "A Multigrid Method for Efficiently Training Video Models", "published_by": "Computer Vision and Pattern Recognition (CVPR), 2020, 2020", "authors": ["CY Wu", "R Girshick", "K He", "C Feichtenhofer", "P Kr\u00e4henb\u00fchl"], "cited_by_link": "https://scholar.google.com/scholar?oi=bibs&hl=en&cites=2801918111473713808", "cited_by": 104, "year": 2020}, {"title_link": "https://scholar.google.com/citations?view_op=view_citation&hl=en&user=DhtAFkwAAAAJ&cstart=20&pagesize=80&citation_for_view=DhtAFkwAAAAJ:2tRrZ1ZAMYUC", "title": "Sparse Projections for High-Dimensional Binary Codes", "published_by": "Computer Vision and Pattern Recognition (CVPR), 2015, 2015", "authors": ["Y Xia", "K He", "P Kohli", "J Sun"], "cited_by_link": "https://scholar.google.com/scholar?oi=bibs&hl=en&cites=12836207512610738761", "cited_by": 102, "year": 2015}, {"title_link": "https://scholar.google.com/citations?view_op=view_citation&hl=en&user=DhtAFkwAAAAJ&cstart=20&pagesize=80&citation_for_view=DhtAFkwAAAAJ:8Xgff_V0N9gC", "title": "Benchmarking Detection Transfer Learning with Vision Transformers", "published_by": "arXiv preprint arXiv:2111.11429, 2021", "authors": ["Y Li", "S Xie", "X Chen", "P Dollar", "K He", "R Girshick"], "cited_by_link": "https://scholar.google.com/scholar?oi=bibs&hl=en&cites=467066746241725706", "cited_by": 101, "year": 2021}, {"title_link": "https://scholar.google.com/citations?view_op=view_citation&hl=en&user=DhtAFkwAAAAJ&cstart=20&pagesize=80&citation_for_view=DhtAFkwAAAAJ:KlAtU1dfN6UC", "title": "Joint Inverted Indexing", "published_by": "International Conference on Computer Vision (ICCV), 2013, 2013", "authors": ["Y Xia", "K He", "F Wen", "J Sun"], "cited_by_link": "https://scholar.google.com/scholar?oi=bibs&hl=en&cites=765227343650566720", "cited_by": 86, "year": 2013}, {"title_link": "https://scholar.google.com/citations?view_op=view_citation&hl=en&user=DhtAFkwAAAAJ&cstart=20&pagesize=80&citation_for_view=DhtAFkwAAAAJ:DkZNVXde3BIC", "title": "Are Labels Necessary for Neural Architecture Search?", "published_by": "European Conference on Computer Vision (ECCV), 2020, 2020", "authors": ["C Liu", "P Doll\u00e1r", "K He", "R Girshick", "A Yuille", "S Xie"], "cited_by_link": "https://scholar.google.com/scholar?oi=bibs&hl=en&cites=7756621635676011996", "cited_by": 76, "year": 2020}, {"title_link": "https://scholar.google.com/citations?view_op=view_citation&hl=en&user=DhtAFkwAAAAJ&cstart=20&pagesize=80&citation_for_view=DhtAFkwAAAAJ:5MTHONV0fEkC", "title": "Graph Cuts for Supervised Binary Coding", "published_by": "European Conference on Computer Vision (ECCV), 2014, 2014", "authors": ["T Ge", "K He", "J Sun"], "cited_by_link": "https://scholar.google.com/scholar?oi=bibs&hl=en&cites=3402185095053676131", "cited_by": 75, "year": 2014}, {"title_link": "https://scholar.google.com/citations?view_op=view_citation&hl=en&user=DhtAFkwAAAAJ&cstart=20&pagesize=80&citation_for_view=DhtAFkwAAAAJ:w0F2JDEymm0C", "title": "GLoMo: unsupervised learning of transferable relational graphs", "published_by": "Neural Information Processing Systems (NIPS), 2018, 2018", "authors": ["Z Yang", "J Zhao", "B Dhingra", "K He", "WW Cohen", "RR Salakhutdinov", "..."], "cited_by_link": "https://scholar.google.com/scholar?oi=bibs&hl=en&cites=958782425356507244,2917732707325476709", "cited_by": 65, "year": 2018}, {"title_link": "https://scholar.google.com/citations?view_op=view_citation&hl=en&user=DhtAFkwAAAAJ&cstart=20&pagesize=80&citation_for_view=DhtAFkwAAAAJ:EsEWqaRxkBgC", "title": "Scaling Language-Image Pre-training via Masking", "published_by": "Computer Vision and Pattern Recognition (CVPR), 2023, 2023", "authors": ["Y Li", "H Fan", "R Hu", "C Feichtenhofer", "K He"], "cited_by_link": "https://scholar.google.com/scholar?oi=bibs&hl=en&cites=8649528985577473031", "cited_by": 59, "year": 2023}, {"title_link": "https://scholar.google.com/citations?view_op=view_citation&hl=en&user=DhtAFkwAAAAJ&cstart=20&pagesize=80&citation_for_view=DhtAFkwAAAAJ:YOwf2qJgpHMC", "title": "Content-Aware Rotation", "published_by": "International Conference on Computer Vision (ICCV), 2013, 2013", "authors": ["K He", "H Chang", "J Sun"], "cited_by_link": "https://scholar.google.com/scholar?oi=bibs&hl=en&cites=15102535070283703580,1686947421222382563", "cited_by": 29, "year": 2013}, {"title_link": "https://scholar.google.com/citations?view_op=view_citation&hl=en&user=DhtAFkwAAAAJ&cstart=20&pagesize=80&citation_for_view=DhtAFkwAAAAJ:4X0JR2_MtJMC", "title": "A Geodesic-Preserving Method for Image Warping", "published_by": "Computer Vision and Pattern Recognition (CVPR), 2015, 2015", "authors": ["D Li", "K He", "J Sun", "K Zhou"], "cited_by_link": "https://scholar.google.com/scholar?oi=bibs&hl=en&cites=8620224707278324381", "cited_by": 28, "year": 2015}, {"title_link": "https://scholar.google.com/citations?view_op=view_citation&hl=en&user=DhtAFkwAAAAJ&cstart=20&pagesize=80&citation_for_view=DhtAFkwAAAAJ:_OXeSy2IsFwC", "title": "Product Sparse Coding", "published_by": "Computer Vision and Pattern Recognition (CVPR), 2014, 2014", "authors": ["T Ge", "K He", "J Sun"], "cited_by_link": "https://scholar.google.com/scholar?oi=bibs&hl=en&cites=7929298595769668040", "cited_by": 28, "year": 2014}], "citation_statistics": {"table": {"": ["Citations", "h-index", "i10-index"], "All": ["492900", "67", "72"], "Since 2018": ["460989", "64", "72"]}, "chart": {}}, "co_authors": [{"link": "https://scholar.google.com/citations?hl=en&user=ALVSZAYAAAAJ", "name": "Jian Sun", "ext": "Chief Scientist of Megvii, Managing Director of Megvii Research"}, {"link": "https://scholar.google.com/citations?hl=en&user=W8VIEZgAAAAJ", "name": "Ross Girshick", "ext": "Research Scientist, Facebook AI Research (FAIR)"}, {"link": "https://scholar.google.com/citations?hl=en&user=AUhj438AAAAJ", "name": "Shaoqing Ren", "ext": "NIO"}, {"link": "https://scholar.google.com/citations?hl=en&user=a8Y2OJMAAAAJ", "name": "Piotr Doll\u00e1r", "ext": "FAIR"}, {"link": "https://scholar.google.com/citations?hl=en&user=yuB-cfoAAAAJ", "name": "Xiangyu Zhang", "ext": "Principal Researcher, MEGVII Technology"}, {"link": "https://scholar.google.com/citations?hl=en&user=kQisE-gAAAAJ", "name": "Georgia Gkioxari", "ext": "Caltech"}, {"link": "https://scholar.google.com/citations?hl=en&user=_BPdgV0AAAAJ", "name": "Tsung-Yi Lin", "ext": "Research Scientist, NVIDIA"}, {"link": "https://scholar.google.com/citations?hl=en&user=qpBtpGsAAAAJ", "name": "Xiaoou Tang", "ext": "The Chinese University of Hong Kong"}, {"link": "https://scholar.google.com/citations?hl=en&user=76B8lrgAAAAJ", "name": "Haoqi Fan", "ext": "Facebook AI Research"}, {"link": "https://scholar.google.com/citations?hl=en&user=Y2GtJkAAAAAJ", "name": "Saining Xie", "ext": "Assistant Professor at the Courant Institute, New York University"}, {"link": "https://scholar.google.com/citations?hl=en&user=SH_-B_AAAAAJ", "name": "Jifeng Dai", "ext": "Associate Professor of EE, Tsinghua University; Adjuct Researcher of Shanghai AI\u00a0\u2026"}, {"link": "https://scholar.google.com/citations?hl=en&user=bSU7LYoAAAAJ", "name": "Xinlei Chen", "ext": "FAIR, Meta"}, {"link": "https://scholar.google.com/citations?hl=en&user=TpglobcAAAAJ", "name": "bharath hariharan", "ext": "Cornell University"}, {"link": "https://scholar.google.com/citations?hl=en&user=chD5XxkAAAAJ", "name": "Serge Belongie", "ext": "University of Copenhagen"}, {"link": "https://scholar.google.com/citations?hl=en&user=mJQI-gUAAAAJ", "name": "Yuxin Wu", "ext": ""}, {"link": "https://scholar.google.com/citations?hl=en&user=UxuqG1EAAAAJ", "name": "Christoph Feichtenhofer", "ext": "Research Scientist, Facebook AI Research (FAIR)"}, {"link": "https://scholar.google.com/citations?hl=en&user=-VgS8AIAAAAJ", "name": "Yanghao Li", "ext": "Facebook AI Research (FAIR)"}, {"link": "https://scholar.google.com/citations?hl=en&user=559LF80AAAAJ", "name": "Chen Change Loy", "ext": "MMLab@NTU, S-Lab, Nanyang Technological University"}, {"link": "https://scholar.google.com/citations?hl=en&user=OSDCB0UAAAAJ", "name": "Chao Dong", "ext": "Shenzhen Institutes of Advanced Technology, Chinese Academy of Sciences"}, {"link": "https://scholar.google.com/citations?hl=en&user=9oz-dvgAAAAJ", "name": "Zhuowen Tu", "ext": "Professor, Cognitive Science, Computer Science&Engineering, UC San Diego"}, {"link": "https://scholar.google.com/citations?hl=en&user=bHn29ScAAAAJ", "name": "Alexander Kirillov", "ext": "Research Scientist, Facebook AI Research (FAIR)"}, {"link": "https://scholar.google.com/citations?hl=en&user=bqL73OkAAAAJ", "name": "Abhinav Gupta", "ext": "Associate Professor, Robotics Institute, Carnegie Mellon University"}, {"link": "https://scholar.google.com/citations?hl=en&user=Y8O9N_0AAAAJ", "name": "Xiaolong Wang", "ext": "Assistant Professor, UC San Diego"}, {"link": "https://scholar.google.com/citations?hl=en&user=MW36lZUAAAAJ", "name": "Yi Li", "ext": "University of Washington"}, {"link": "https://scholar.google.com/citations?hl=en&user=N_YNMIMAAAAJ", "name": "Carsten Rother", "ext": "Professor Uni Heidelberg / Germany"}, {"link": "https://scholar.google.com/citations?hl=en&user=aOklxsQAAAAJ", "name": "Jitendra MALIK", "ext": "Professor of EECS, UC Berkeley"}, {"link": "https://scholar.google.com/citations?hl=en&user=UKpinl8AAAAJ", "name": "Ilija Radosavovic", "ext": "PhD Student, UC Berkeley"}, {"link": "https://scholar.google.com/citations?hl=en&user=mu5Y2rYAAAAJ", "name": "Yangqing Jia", "ext": "VP, Alibaba Group"}, {"link": "https://scholar.google.com/citations?hl=en&user=duSEbnYAAAAJ", "name": "Andrew Tulloch", "ext": "Facebook AI Research group"}, {"link": "https://scholar.google.com/citations?hl=en&user=vKlrdpEAAAAJ", "name": "Aapo Kyrola", "ext": "Ph.D (Carnegie Mellon University, 2014)"}, {"link": "https://scholar.google.com/citations?hl=en&user=j5_DDM0AAAAJ", "name": "Lukasz Wesolowski", "ext": "Research Scientist, Facebook"}, {"link": "https://scholar.google.com/citations?hl=en&user=db5ZTlMAAAAJ", "name": "Tiezheng Ge", "ext": "Staff algorithm engineer, Alimama, Alibaba Group"}, {"link": "https://scholar.google.com/citations?hl=en&user=6GDfcqEAAAAJ", "name": "Laurens van der Maaten", "ext": "Distinguished Research Scientist, Meta AI"}, {"link": "https://scholar.google.com/citations?hl=en&user=ZFW98t4AAAAJ", "name": "Bo Xiong", "ext": "Facebook AI Research (FAIR)"}, {"link": "https://scholar.google.com/citations?hl=en&user=5FwRvZAAAAAJ", "name": "Raj Prateek Kosaraju", "ext": "Facebook AI Research"}, {"link": "https://scholar.google.com/citations?hl=en&user=FJ-huxgAAAAJ", "name": "Alan Yuille", "ext": "Professor of Cognitive Science and Computer Science, Johns Hopkins University"}, {"link": "https://scholar.google.com/citations?hl=en&user=gnL-jX0AAAAJ", "name": "Qifa Ke", "ext": "Uber"}, {"link": "https://scholar.google.com/citations?hl=en&user=Zdl00bEAAAAJ", "name": "Vignesh Ramanathan", "ext": "Research Scientist at Facebook"}, {"link": "https://scholar.google.com/citations?hl=en&user=Gd9HQn2UsNoC", "name": "Dhruv Mahajan", "ext": "Research Director, Facebook AI Research (FAIR)"}, {"link": "https://scholar.google.com/citations?hl=en&user=QSTd1oUAAAAJ", "name": "Sharon Yixuan Li", "ext": "University of Wisconsin-Madison"}, {"link": "https://scholar.google.com/citations?hl=en&user=TV9sa6QAAAAJ", "name": "Manohar Paluri", "ext": "Facebook"}, {"link": "https://scholar.google.com/citations?hl=en&user=dzOd2hgAAAAJ", "name": "Philipp Kr\u00e4henb\u00fchl", "ext": "UT Austin"}, {"link": "https://scholar.google.com/citations?hl=en&user=QiJPlOIAAAAJ", "name": "Chao-Yuan Wu", "ext": "Research Scientist, the FAIR team @ Meta AI"}, {"link": "https://scholar.google.com/citations?hl=en&user=XPAkzTEAAAAJ", "name": "Jiaya Jia", "ext": "Professor, CUHK"}, {"link": "https://scholar.google.com/citations?hl=en&user=rW0r-hMAAAAJ", "name": "Di Lin", "ext": "Associate Professor, Tianjin University"}, {"link": "https://scholar.google.com/citations?hl=en&user=Ihs8dwsAAAAJ", "name": "Or Litany", "ext": "Technion, NVIDIA"}, {"link": "https://scholar.google.com/citations?hl=en&user=4jODkxsAAAAJ", "name": "Charles Ruizhongtai Qi", "ext": "Research Scientist, Waymo"}, {"link": "https://scholar.google.com/citations?hl=en&user=5JlEyTAAAAAJ", "name": "Leonidas Guibas", "ext": "Professor of Computer Science, Stanford University"}, {"link": "https://scholar.google.com/citations?hl=en&user=eZQNcvcAAAAJ", "name": "Huiwen Chang", "ext": "OpenAI"}, {"link": "https://scholar.google.com/citations?hl=en&user=iO6xAdgAAAAJ", "name": "Liliang Zhang", "ext": "DJI"}, {"link": "https://scholar.google.com/citations?hl=en&user=X3vVZPcAAAAJ", "name": "Cihang Xie", "ext": "Assistant Professor, University of California, Santa Cruz"}, {"link": "https://scholar.google.com/citations?hl=en&user=rTw-pq0AAAAJ", "name": "Ronghang Hu", "ext": "Research Scientist, Meta AI"}, {"link": "https://scholar.google.com/citations?hl=en&user=5D0_pjcAAAAJ", "name": "Christoph Rhemann", "ext": "Research Scientist, Google"}, {"link": "https://scholar.google.com/citations?hl=en&user=K8oom-cAAAAJ", "name": "Yan Xia", "ext": "Momenta"}, {"link": "https://scholar.google.com/citations?hl=en&user=O7A6nYMAAAAJ", "name": "Yichen Wei", "ext": "SHUKUN Technology"}, {"link": "https://scholar.google.com/citations?hl=en&user=t_gZZTsAAAAJ", "name": "Ziyang Ma", "ext": "Tencent"}, {"link": "https://scholar.google.com/citations?hl=en&user=bh-uRFMAAAAJ", "name": "Trevor Darrell", "ext": "Professor of Computer Science, UC Berkeley"}, {"link": "https://scholar.google.com/citations?hl=en&user=7qXxyJkAAAAJ", "name": "Zhilin Yang", "ext": "Carnegie Mellon University"}, {"link": "https://scholar.google.com/citations?hl=en&user=WLN3QrAAAAAJ", "name": "Yann LeCun", "ext": "Chief AI Scientist at Facebook & Silver Professor at the Courant Institute, New York\u00a0\u2026"}, {"link": "https://scholar.google.com/citations?hl=en&user=ITZ1e7MAAAAJ", "name": "Ruslan Salakhutdinov", "ext": "UPMC Professor, Machine Learning Department, CMU"}, {"link": "https://scholar.google.com/citations?hl=en&user=8ys-38kAAAAJ", "name": "William W. Cohen", "ext": "Google AI"}, {"link": "https://scholar.google.com/citations?hl=en&user=8ipao8MAAAAJ", "name": "Junbo Zhao", "ext": "Zhejiang University, ZJU100 Young Professor"}, {"link": "https://scholar.google.com/citations?hl=en&user=Q_kKkIUAAAAJ", "name": "Jure Leskovec", "ext": "Professor of Computer Science, Stanford University"}, {"link": "https://scholar.google.com/citations?hl=en&user=NDbMl7oAAAAJ", "name": "Jiaxuan You", "ext": "Incoming Assistant Professor, UIUC CS"}, {"link": "https://scholar.google.com/citations?hl=en&user=3pyzQQ8AAAAJ", "name": "Pushmeet Kohli", "ext": "DeepMind"}, {"link": "https://scholar.google.com/citations?hl=en&user=qvRsU00AAAAJ", "name": "Chenxi Liu", "ext": "Research Scientist, Google DeepMind"}, {"link": "https://scholar.google.com/citations?hl=en&user=N-iYby0AAAAJ", "name": "Kun Zhou", "ext": "Professor of Computer Science, Zhejiang University"}], "interests": ["Computer Vision", "Machine Learning"], "link": "https://scholar.google.com/citations?hl=en&user=DhtAFkwAAAAJ", "name": "Kaiming He", "affiliates": [], "last_updated": "2023/10/31 20:28"}